tabspy/__init__.py
tabspy/utils.py
tabspy/strategy/__init__.py
tabspy/strategy/strategy.py
tabspy-0.0.2.dist-info/LICENSE.txt
tabspy-0.0.2.dist-info/METADATA
tabspy-0.0.2.dist-info/WHEEL
tabspy-0.0.2.dist-info/top_level.txt
tabspy-0.0.2.dist-info/RECORD
