Metadata-Version: 2.1
Name: tabspy
Version: 0.0.2
Summary: TABSPY by SB
Home-page: UNKNOWN
Author: tabspy
License: The MIT License (MIT)
Platform: UNKNOWN
Classifier: Programming Language :: Python :: 3
Classifier: Programming Language :: Python :: 3.5
Classifier: License :: OSI Approved :: MIT License
Requires-Dist: numpy
